LICENSE
README.md
setup.py
src/checkpoint_tools/__init__.py
src/checkpoint_tools/__main__.py
src/checkpoint_tools.egg-info/PKG-INFO
src/checkpoint_tools.egg-info/SOURCES.txt
src/checkpoint_tools.egg-info/dependency_links.txt
src/checkpoint_tools.egg-info/entry_points.txt
src/checkpoint_tools.egg-info/requires.txt
src/checkpoint_tools.egg-info/top_level.txt
src/checkpoint_tools/util/__init__.py
src/checkpoint_tools/util/diffusers_util.py
src/checkpoint_tools/util/dtype_util.py
src/checkpoint_tools/util/dummy_util.py
src/checkpoint_tools/util/log_util.py
src/checkpoint_tools/util/state_dict_util.py
src/checkpoint_tools/util/terminal_util.py